universal_intelligence/__init__.py
universal_intelligence/community/__utils__/logger.py
universal_intelligence/community/agents/__utils__/test.py
universal_intelligence/community/agents/default/__init__.py
universal_intelligence/community/agents/default/test.py
universal_intelligence/community/agents/simple_agent/__init__.py
universal_intelligence/community/agents/simple_agent/agent.py
universal_intelligence/community/agents/simple_agent/test.py
universal_intelligence/community/models/__utils__/test.py
universal_intelligence/community/models/__utils__/mixins/hf_text_to_text/interface.py
universal_intelligence/community/models/__utils__/mixins/hf_text_to_text/meta.py
universal_intelligence/community/models/__utils__/mixins/hf_text_to_text/types.py
universal_intelligence/community/models/default/__init__.py
universal_intelligence/community/models/default/test.py
universal_intelligence/community/models/falcon3_10b_instruct/__init__.py
universal_intelligence/community/models/falcon3_10b_instruct/model.py
universal_intelligence/community/models/falcon3_10b_instruct/sources.yaml
universal_intelligence/community/models/falcon3_10b_instruct/test.py
universal_intelligence/community/models/falcon3_3b_instruct/__init__.py
universal_intelligence/community/models/falcon3_3b_instruct/model.py
universal_intelligence/community/models/falcon3_3b_instruct/sources.yaml
universal_intelligence/community/models/falcon3_3b_instruct/test.py
universal_intelligence/community/models/falcon3_7b_instruct/__init__.py
universal_intelligence/community/models/falcon3_7b_instruct/model.py
universal_intelligence/community/models/falcon3_7b_instruct/sources.yaml
universal_intelligence/community/models/falcon3_7b_instruct/test.py
universal_intelligence/community/models/gemma3_12b_it/__init__.py
universal_intelligence/community/models/gemma3_12b_it/model.py
universal_intelligence/community/models/gemma3_12b_it/sources.yaml
universal_intelligence/community/models/gemma3_12b_it/test.py
universal_intelligence-0.5.0.dist-info/METADATA
universal_intelligence-0.5.0.dist-info/WHEEL
universal_intelligence-0.5.0.dist-info/licenses/LICENSE
universal_intelligence-0.5.0.dist-info/RECORD
