Metadata-Version: 2.4
Name: universal-intelligence
Version: 0.5.0
Summary: Universal Intelligence
Project-URL: Homepage, https://github.com/blueraai/universal-intelligence
Project-URL: Bug Tracker, https://github.com/blueraai/universal-intelligence/issues
Author-email: "Bluera Inc." <bluera@bluera.ai>
License: Copyright 2025 Bluera Inc. | All rights reserved.
License-File: LICENSE
Classifier: License :: OSI Approved :: Apache Software License
Classifier: Operating System :: OS Independent
Classifier: Programming Language :: Python :: 3
Requires-Python: <3.13,>=3.10
Provides-Extra: community
Requires-Dist: accelerate; extra == 'community'
Requires-Dist: huggingface-hub; extra == 'community'
Requires-Dist: llama-cpp-python; extra == 'community'
Requires-Dist: protobuf; extra == 'community'
Requires-Dist: psutil; extra == 'community'
Requires-Dist: torch; extra == 'community'
Requires-Dist: transformers; extra == 'community'
Provides-Extra: cuda
Requires-Dist: accelerate; extra == 'cuda'
Requires-Dist: auto-gptq; extra == 'cuda'
Requires-Dist: autoawq; extra == 'cuda'
Requires-Dist: bitsandbytes; extra == 'cuda'
Requires-Dist: llama-cpp-python; extra == 'cuda'
Requires-Dist: optimum; extra == 'cuda'
Provides-Extra: dev
Requires-Dist: black>=24.2.0; extra == 'dev'
Requires-Dist: isort>=5.13.2; extra == 'dev'
Requires-Dist: ruff>=0.3.0; extra == 'dev'
Provides-Extra: mcp
Requires-Dist: mcp; extra == 'mcp'
Provides-Extra: mps
Requires-Dist: mlx; extra == 'mps'
Requires-Dist: mlx-lm; extra == 'mps'
